LICENSE
MANIFEST.in
README.md
setup.py
zdir.py
zdir.egg-info/PKG-INFO
zdir.egg-info/SOURCES.txt
zdir.egg-info/dependency_links.txt
zdir.egg-info/top_level.txt