Metadata-Version: 1.0
Name: zdir
Version: 0.0.4
Summary: Library for handling many small files. Packs files into directory, nameing by hash of content. 
Home-page: https://github.com/oskarnyqvist/zdir
Author: oskarnyqvist
Author-email: oskarnyqvist@gmail.com
License: The MIT License (MIT)
